{
	"schemaVersion": 1,
	"id": "skyupplus",
	"version": "${version}",
	"name": "SkyUpPlus",
	"description": "This is an example description! Tell everyone what your mod is about!",
	"authors": [
		"Me!"
	],
	"contact": {
		"homepage": "",
		"sources": "https://github.com/Galgan05/SkyUpPlus-1.21.8"
	},
	"license": "CC0-1.0",
	"icon": "assets/skyupextras/icon.png",
	"environment": "*",
	"entrypoints": {
		"client": [
          "net.galgan.skyupplus.SkyUpPlusClient"
		],
		"fabric-datagen": [
			"net.galgan.skyupplus.SkyUpPlusDataGenerator"
		]
	},
	"mixins": [
		"skyupplus.mixins.json"
	],
	"depends": {
		"fabricloader": ">=0.17.2",
		"minecraft": "~1.21.8",
		"java": ">=21",
		"fabric-api": "*"
	},
	"suggests": {
		"another-mod": "*"
	}
}